jaxwt/__init__.py
jaxwt/continuous_transform.py
jaxwt/conv_fwt.py
jaxwt/conv_fwt_2d.py
jaxwt/conv_fwt_3d.py
jaxwt/packets.py
jaxwt/stationary_transform.py
jaxwt/utils.py
jaxwt/version.py
jaxwt-0.1.1.dist-info/LICENSE
jaxwt-0.1.1.dist-info/METADATA
jaxwt-0.1.1.dist-info/WHEEL
jaxwt-0.1.1.dist-info/top_level.txt
jaxwt-0.1.1.dist-info/RECORD
