Metadata-Version: 2.1
Name: jaxwt
Version: 0.1.1
Summary: Differentiable and gpu enabled fast wavelet transforms in JAX
Home-page: https://github.com/v0lta/Jax-Wavelet-Toolbox
Download-URL: https://github.com/v0lta/Jax-Wavelet-Toolbox/releases
Author: Moritz Wolter
Author-email: moritz@wolter.tech
Maintainer: Moritz Wolter
Maintainer-email: moritz@wolter.tech
License: EUPL-1.2
Project-URL: Bug Tracker, https://github.com/v0lta/Jax-Wavelet-Toolbox/issues
Project-URL: Source Code, https://github.com/v0lta/Jax-Wavelet-Toolbox
Keywords: Wavelets,Wavelet Transform,Fast Wavelet Transform,Jax
Classifier: License :: OSI Approved :: European Union Public Licence 1.2 (EUPL 1.2)
Classifier: Development Status :: 4 - Beta
Classifier: Environment :: Console
Classifier: Intended Audience :: Science/Research
Classifier: Operating System :: OS Independent
Classifier: Programming Language :: Python
Classifier: Programming Language :: Python :: 3.9
Classifier: Programming Language :: Python :: 3.11
Classifier: Programming Language :: Python :: 3 :: Only
Classifier: Topic :: Scientific/Engineering
Requires-Python: >=3.9
License-File: LICENSE
Requires-Dist: PyWavelets
Requires-Dist: jax
Requires-Dist: jaxlib
Requires-Dist: numpy
Provides-Extra: jax_cpu
Requires-Dist: jax ; extra == 'jax_cpu'
Requires-Dist: jaxlib ; extra == 'jax_cpu'
